tf_attention_layer/__init__.py
tf_attention_layer/keras_utils.py
tf_attention_layer/layers/__init__.py
tf_attention_layer/layers/global_attentioin_layer.py
tf_attention_layer-0.1.2.dist-info/METADATA
tf_attention_layer-0.1.2.dist-info/WHEEL
tf_attention_layer-0.1.2.dist-info/top_level.txt
tf_attention_layer-0.1.2.dist-info/RECORD
