Metadata-Version: 2.1
Name: tf-attention-layer
Version: 0.1.2
Summary: Attention layer for TensorFlow 1.x
Home-page: https://github.com/howl-anderson/tf_attention_layer
Author: Xiaoquan Kong
Author-email: u1mail2me@gmail.com
License: MIT
Platform: UNKNOWN
Requires-Dist: tensorflow
Requires-Dist: tokenizer-tools
